dynacir/__init__.py
dynacir/dynacir_noisemodel.py
dynacir/dynacir_passes.py
dynacir/dynacir_plugin.py
dynacir-0.1.4.dist-info/LICENSE
dynacir-0.1.4.dist-info/METADATA
dynacir-0.1.4.dist-info/WHEEL
dynacir-0.1.4.dist-info/entry_points.txt
dynacir-0.1.4.dist-info/top_level.txt
dynacir-0.1.4.dist-info/RECORD
