Metadata-Version: 2.1
Name: dynacir
Version: 0.1.4
Summary: A Qiskit transpilation plugin for `dyna`mic `cir`cuits.
Author-email: Derek Wang <derek.wang@ibm.com>
License: Copyright 2022 IBM and its contributors
Project-URL: Repository, https://github.com/derek-wang-ibm/dynacir
Keywords: qiskit,quantum,plugin
Classifier: Programming Language :: Python :: 3
Classifier: License :: OSI Approved :: Apache Software License
Classifier: Operating System :: OS Independent
License-File: LICENSE
